{"artist":{"name":"Delirious","mbid":"e6fd85aa-b997-4252-b78b-f61eb2150a6d","url":"https://www.last.fm/music/Delirious","image":[{"#text":"https://lastfm-img2.akamaized.net/i/u/34s/8d2233204f52479dbc93b93f3cfd2c0c.png","size":"small"},{"#text":"https://lastfm-img2.akamaized.net/i/u/64s/8d2233204f52479dbc93b93f3cfd2c0c.png","size":"medium"},{"#text":"https://lastfm-img2.akamaized.net/i/u/174s/8d2233204f52479dbc93b93f3cfd2c0c.png","size":"large"},{"#text":"https://lastfm-img2.akamaized.net/i/u/300x300/8d2233204f52479dbc93b93f3cfd2c0c.png","size":"extralarge"},{"#text":"https://lastfm-img2.akamaized.net/i/u/300x300/8d2233204f52479dbc93b93f3cfd2c0c.png","size":"mega"},{"#text":"https://lastfm-img2.akamaized.net/i/u/300x300/8d2233204f52479dbc93b93f3cfd2c0c.png","size":""}],"streamable":"0","ontour":"0","stats":{"listeners":"46873","playcount":"432985"},"similar":{"artist":[{"name":"Delirious?","url":"https://www.last.fm/music/Delirious%3F","image":[{"#text":"https://lastfm-img2.akamaized.net/i/u/34s/ca74930143a34fd8b396bd11ecf3ea50.png","size":"small"},{"#text":"https://lastfm-img2.akamaized.net/i/u/64s/ca74930143a34fd8b396bd11ecf3ea50.png","size":"medium"},{"#text":"https://lastfm-img2.akamaized.net/i/u/174s/ca74930143a34fd8b396bd11ecf3ea50.png","size":"large"},{"#text":"https://lastfm-img2.akamaized.net/i/u/300x300/ca74930143a34fd8b396bd11ecf3ea50.png","size":"extralarge"},{"#text":"https://lastfm-img2.akamaized.net/i/u/300x300/ca74930143a34fd8b396bd11ecf3ea50.png","size":"mega"},{"#text":"https://lastfm-img2.akamaized.net/i/u/300x300/ca74930143a34fd8b396bd11ecf3ea50.png","size":""}]},{"name":"Psycraft","url":"https://www.last.fm/music/Psycraft","image":[{"#text":"https://lastfm-img2.akamaized.net/i/u/34s/acdcb0e966aa4eaa8fc955ebface2a80.png","size":"small"},{"#text":"https://lastfm-img2.akamaized.net/i/u/64s/acdcb0e966aa4eaa8fc955ebface2a80.png","size":"medium"},{"#text":"https://lastfm-img2.akamaized.net/i/u/174s/acdcb0e966aa4eaa8fc955ebface2a80.png","size":"large"},{"#text":"https://lastfm-img2.akamaized.net/i/u/300x300/acdcb0e966aa4eaa8fc955ebface2a80.png","size":"extralarge"},{"#text":"https://lastfm-img2.akamaized.net/i/u/300x300/acdcb0e966aa4eaa8fc955ebface2a80.png","size":"mega"},{"#text":"https://lastfm-img2.akamaized.net/i/u/300x300/acdcb0e966aa4eaa8fc955ebface2a80.png","size":""}]},{"name":"Astrix","url":"https://www.last.fm/music/Astrix","image":[{"#text":"https://lastfm-img2.akamaized.net/i/u/34s/37062a2a5ef94dea8ba5631817393bdc.png","size":"small"},{"#text":"https://lastfm-img2.akamaized.net/i/u/64s/37062a2a5ef94dea8ba5631817393bdc.png","size":"medium"},{"#text":"https://lastfm-img2.akamaized.net/i/u/174s/37062a2a5ef94dea8ba5631817393bdc.png","size":"large"},{"#text":"https://lastfm-img2.akamaized.net/i/u/300x300/37062a2a5ef94dea8ba5631817393bdc.png","size":"extralarge"},{"#text":"https://lastfm-img2.akamaized.net/i/u/300x300/37062a2a5ef94dea8ba5631817393bdc.png","size":"mega"},{"#text":"https://lastfm-img2.akamaized.net/i/u/300x300/37062a2a5ef94dea8ba5631817393bdc.png","size":""}]},{"name":"Third Day","url":"https://www.last.fm/music/Third+Day","image":[{"#text":"https://lastfm-img2.akamaized.net/i/u/34s/88552a4fa4d528511aa51a473a2e0e01.png","size":"small"},{"#text":"https://lastfm-img2.akamaized.net/i/u/64s/88552a4fa4d528511aa51a473a2e0e01.png","size":"medium"},{"#text":"https://lastfm-img2.akamaized.net/i/u/174s/88552a4fa4d528511aa51a473a2e0e01.png","size":"large"},{"#text":"https://lastfm-img2.akamaized.net/i/u/300x300/88552a4fa4d528511aa51a473a2e0e01.png","size":"extralarge"},{"#text":"https://lastfm-img2.akamaized.net/i/u/300x300/88552a4fa4d528511aa51a473a2e0e01.png","size":"mega"},{"#text":"https://lastfm-img2.akamaized.net/i/u/300x300/88552a4fa4d528511aa51a473a2e0e01.png","size":""}]},{"name":"Rebecca St. James","url":"https://www.last.fm/music/Rebecca+St.+James","image":[{"#text":"https://lastfm-img2.akamaized.net/i/u/34s/63ec30946d104c5385401b9a06e9847a.png","size":"small"},{"#text":"https://lastfm-img2.akamaized.net/i/u/64s/63ec30946d104c5385401b9a06e9847a.png","size":"medium"},{"#text":"https://lastfm-img2.akamaized.net/i/u/174s/63ec30946d104c5385401b9a06e9847a.png","size":"large"},{"#text":"https://lastfm-img2.akamaized.net/i/u/300x300/63ec30946d104c5385401b9a06e9847a.png","size":"extralarge"},{"#text":"https://lastfm-img2.akamaized.net/i/u/300x300/63ec30946d104c5385401b9a06e9847a.png","size":"mega"},{"#text":"https://lastfm-img2.akamaized.net/i/u/300x300/63ec30946d104c5385401b9a06e9847a.png","size":""}]}]},"tags":{"tag":[{"name":"christian","url":"https://www.last.fm/tag/christian"},{"name":"thrash metal","url":"https://www.last.fm/tag/thrash+metal"},{"name":"psychedelic","url":"https://www.last.fm/tag/psychedelic"},{"name":"psytrance","url":"https://www.last.fm/tag/psytrance"},{"name":"worship","url":"https://www.last.fm/tag/worship"}]},"bio":{"links":{"link":{"#text":"","rel":"original","href":"https://last.fm/music/Delirious/+wiki"}},"published":"14 Aug 2007, 11:35","summary":"There are at least two projects with the name Delirious: a German thrash metal band and an Israeli psychedelic trance duo. These projects should not be confused with the band Delirious?.\n\n1. Delirious is a thrash metal band from Germany formed in 1990. It consists of band members Andreas Supplie (Guitar), Markus Keller (Drums),  Markus \"Betty\" Bednarek (Vocals),  Christian \"Spletty\" Splettstößer (Bass),  Alex Cwiertnia (Guitar) and have their beginnings from Testament <a href=\"https://www.last.fm/music/Delirious\">Read more on Last.fm</a>","content":"There are at least two projects with the name Delirious: a German thrash metal band and an Israeli psychedelic trance duo. These projects should not be confused with the band Delirious?.\n\n1. Delirious is a thrash metal band from Germany formed in 1990. It consists of band members Andreas Supplie (Guitar), Markus Keller (Drums),  Markus \"Betty\" Bednarek (Vocals),  Christian \"Spletty\" Splettstößer (Bass),  Alex Cwiertnia (Guitar) and have their beginnings from Testament, Forbidden and Heathen and melodic elements from Blind Guardian and Gamma Ray.\n\nOfficial website of Delirious:\nhttp://www.delirious.de/\n\n2. Avi Harush (a.k.a DJ Tshompi) and Arik Mimone are from the south of Israel and since 1998 they run the ‘Delirious’ project. With three full albums, many collaborations and remixes, and a good deal of live acts at some of the biggest open-air festivals, they have gained a steady ground for their act.\n\nReleased albums:\n - Tales From the Unknown (2001 - Agitato Records)\n - Break Point            (2005 - Hom-Mega Productions)\n - Fast Forward To Rewind (2007 - Hom-Mega Productions)\n - To The Limit (2010 - Hom-Mega Productions) <a href=\"https://www.last.fm/music/Delirious\">Read more on Last.fm</a>. User-contributed text is available under the Creative Commons By-SA License; additional terms may apply."}}}
